{
  "format_version": "1.12",
  "minecraft:recipe_shaped": {
    "description": {
      "identifier": "mc:furniture_cherry_towel_rack_recipe"
    },
    "tags": [
      "furniture_crafting_table"
    ],
    "pattern": [
      "III",
      "WWW",
      "I I"
    ],
    "key": {
      "I": {
        "item": "minecraft:iron_ingot"
      },
      "W": {
        "item": "minecraft:cherry_planks"
      }
    },
    "unlock": [
      {
        "item": "minecraft:cherry_planks"
      }
    ],
    "result": {
      "item": "mc:furniture_cherry_towel_rack",
      "count": 1
    }
  }
}